Metadata-Version: 1.0
Name: andyofmelbourne-pytemplate
Version: 0.0.0
Summary: a simple python template project
Home-page: http://github.com/andyofmelbourne/pytemplate
Author: Andrew Morgan
Author-email: andyofmelbourne@gmail.com
License: MIT License
